out/__init__.py
out/gunicorn_config.py
out/gunicorn_config_test.py
out/project_config.py
out/project_config_flask.py
out/project_train.py
out/test_project_flask.py
out/test_project_flask_local.py
yqn_common/__init__.py
yqn_common/crd_reduction.py
yqn_common/cv_util.py
yqn_common/download_file.py
yqn_common/helper.py
yqn_common/image_util.py
yqn_common/io_util.py
yqn_common/jieba_load_dict.py
yqn_common/logger.py
yqn_common/metric_logger.py
yqn_common/np_util.py
yqn_common/ocr_data_generator_util.py
yqn_common/oss_func.py
yqn_common/singleton.py
yqn_common/space_reduction.py
yqn_common/str_util.py
yqn_common/tool_label_json.py
yqn_common/vocab_util.py
yqn_common/xml_util.py
yqn_config/__init__.py
yqn_config/base_config.py
yqn_config/conf_parser.py
yqn_exception/__init__.py
yqn_exception/exception.py
yqn_ops/__init__.py
yqn_ops/download_resource.py
yqn_pytorch_framework/__init__.py
yqn_pytorch_framework/device.py
yqn_pytorch_framework/pytorch_initialize.py
yqn_pytorch_framework/estimate/__init__.py
yqn_pytorch_framework/estimate/size_estimate.py
yqn_pytorch_framework/estimate/time_estimate.py
yqn_pytorch_framework/export/__init__.py
yqn_pytorch_framework/export/pytorch_to_onnx.py
yqn_pytorch_framework/hub/__init__.py
yqn_pytorch_framework/hub/mobilenet.py
yqn_pytorch_framework/hub/resnet.py
yqn_pytorch_framework/hub/shufflenetv2.py
yqn_pytorch_framework/hub/utils.py
yqn_pytorch_framework/hub/vgg.py
yqn_pytorch_framework/infer/__init__.py
yqn_pytorch_framework/infer/base_infer.py
yqn_pytorch_framework/layer/__init__.py
yqn_pytorch_framework/layer/pytorch_bilstm.py
yqn_pytorch_framework/layer/pytorch_crf.py
yqn_pytorch_framework/layer/pytorch_textcnn_conv.py
yqn_pytorch_framework/layer/pytorch_textcnn_conv_pool.py
yqn_pytorch_framework/model/__init__.py
yqn_pytorch_framework/model/base_model.py
yqn_pytorch_framework/train/__init__.py
yqn_pytorch_framework/train/base_dataset.py
yqn_pytorch_framework/train/base_engine.py
yqn_pytorch_framework/train/base_train.py
yqn_pytorch_framework-0.3.0.dist-info/LICENSE
yqn_pytorch_framework-0.3.0.dist-info/METADATA
yqn_pytorch_framework-0.3.0.dist-info/WHEEL
yqn_pytorch_framework-0.3.0.dist-info/entry_points.txt
yqn_pytorch_framework-0.3.0.dist-info/top_level.txt
yqn_pytorch_framework-0.3.0.dist-info/RECORD
